rerun/__init__.py
rerun/options.py
rerun/rerun.py
rerun/version.py
rerun-1.0.28.dist-info/DESCRIPTION.rst
rerun-1.0.28.dist-info/METADATA
rerun-1.0.28.dist-info/RECORD
rerun-1.0.28.dist-info/WHEEL
rerun-1.0.28.dist-info/entry_points.txt
rerun-1.0.28.dist-info/metadata.json
rerun-1.0.28.dist-info/top_level.txt
rerun-1.0.28.dist-info/zip-safe
